mts_upload/__init__.py
mts_upload/__main__.py
mts_upload-1.0.2.dist-info/METADATA
mts_upload-1.0.2.dist-info/WHEEL
mts_upload-1.0.2.dist-info/entry_points.txt
mts_upload-1.0.2.dist-info/top_level.txt
mts_upload-1.0.2.dist-info/RECORD
