Metadata-Version: 2.4
Name: mts-upload
Version: 1.0.2
Summary: Uploads files to confluence with support for expands.
Author: Ben Bastianelli
Author-email: benbastianelli@gmail.com
Classifier: Programming Language :: Python :: 3
Classifier: Operating System :: OS Independent
Requires-Python: >=3.6
Requires-Dist: markdown>=3.10
Requires-Dist: requests>=2.32.5
Dynamic: author
Dynamic: author-email
Dynamic: classifier
Dynamic: requires-dist
Dynamic: requires-python
Dynamic: summary
